{
  "san-francisco": {
    "sunrise": "7:06 AM",
    "sunset": "6:50 PM",
    "solar_noon": "12:59 PM",
    "civil_twilight_begin": "6:40 AM",
    "civil_twilight_end": "7:16 PM",
    "nautical_twilight_begin": "6:40 AM",
    "nautical_twilight_end": "7:16 PM",
    "astronomical_twilight_begin": "6:40 AM",
    "astronomical_twilight_end": "7:16 PM",
    "day_length": 42213,
    "sunrise_score": 2,
    "sunset_score": 3,
    "moon_phase": {
      "value": 9.21,
      "label": "Waxing Gibbous",
      "moonrise": "4:39 PM",
      "moonset": "1:52 AM"
    },
    "fog_forecast": [
      {
        "time": "2025-10-01T21:00:00",
        "visibility": "unknown",
        "cloud_cover": {
          "total": 66
        },
        "fog_score": 6.6
      },
      {
        "time": "2025-10-01T22:00:00",
        "visibility": "unknown",
        "cloud_cover": {
          "total": 62
        },
        "fog_score": 6.2
      },
      {
        "time": "2025-10-01T23:00:00",
        "visibility": "unknown",
        "cloud_cover": {
          "total": 57
        },
        "fog_score": 5.7
      },
      {
        "time": "2025-10-02T00:00:00",
        "visibility": "unknown",
        "cloud_cover": {
          "total": 96
        },
        "fog_score": 9.6
      },
      {
        "time": "2025-10-02T01:00:00",
        "visibility": "unknown",
        "cloud_cover": {
          "total": 59
        },
        "fog_score": 5.9
      },
      {
        "time": "2025-10-02T02:00:00",
        "visibility": "unknown",
        "cloud_cover": {
          "total": 80
        },
        "fog_score": 8.0
      },
      {
        "time": "2025-10-02T03:00:00",
        "visibility": "unknown",
        "cloud_cover": {
          "total": 92
        },
        "fog_score": 9.2
      },
      {
        "time": "2025-10-02T04:00:00",
        "visibility": "unknown",
        "cloud_cover": {
          "total": 94
        },
        "fog_score": 9.4
      },
      {
        "time": "2025-10-02T05:00:00",
        "visibility": "unknown",
        "cloud_cover": {
          "total": 81
        },
        "fog_score": 8.1
      },
      {
        "time": "2025-10-02T06:00:00",
        "visibility": "unknown",
        "cloud_cover": {
          "total": 79
        },
        "fog_score": 7.9
      },
      {
        "time": "2025-10-02T07:00:00",
        "visibility": "unknown",
        "cloud_cover": {
          "total": 100
        },
        "fog_score": 10.0
      },
      {
        "time": "2025-10-02T08:00:00",
        "visibility": "unknown",
        "cloud_cover": {
          "total": 100
        },
        "fog_score": 10.0
      }
    ],
    "twilight_phases": [
      {
        "label": "Civil Twilight",
        "start": "6:40 AM",
        "end": "7:06 AM",
        "avg_fog_score": null
      },
      {
        "label": "Golden Hour",
        "start": "7:06 AM",
        "end": "8:06 AM",
        "avg_fog_score": null
      }
    ],
    "recommended_shoot_time": null,
    "summary_text": "No optimal low-fog window during twilight today. Consider shooting at sunset or when fog clears.",
    "updated_at": "2025-10-02T04:06:02.098237+00:00"
  },
  "los-angeles": {
    "sunrise": "6:48 AM",
    "sunset": "6:35 PM",
    "solar_noon": "12:42 PM",
    "civil_twilight_begin": "6:23 AM",
    "civil_twilight_end": "7:00 PM",
    "nautical_twilight_begin": "6:23 AM",
    "nautical_twilight_end": "7:00 PM",
    "astronomical_twilight_begin": "6:23 AM",
    "astronomical_twilight_end": "7:00 PM",
    "day_length": 42379,
    "sunrise_score": 5,
    "sunset_score": 5,
    "moon_phase": {
      "value": 9.21,
      "label": "Waxing Gibbous",
      "moonrise": "4:13 PM",
      "moonset": "1:45 AM"
    },
    "fog_forecast": [
      {
        "time": "2025-10-01T21:00:00",
        "visibility": "unknown",
        "cloud_cover": {
          "total": 20
        },
        "fog_score": 2.0
      },
      {
        "time": "2025-10-01T22:00:00",
        "visibility": "unknown",
        "cloud_cover": {
          "total": 12
        },
        "fog_score": 1.2
      },
      {
        "time": "2025-10-01T23:00:00",
        "visibility": "unknown",
        "cloud_cover": {
          "total": 7
        },
        "fog_score": 0.7
      },
      {
        "time": "2025-10-02T00:00:00",
        "visibility": "unknown",
        "cloud_cover": {
          "total": 0.0
        },
        "fog_score": 0.0
      },
      {
        "time": "2025-10-02T01:00:00",
        "visibility": "unknown",
        "cloud_cover": {
          "total": 0.0
        },
        "fog_score": 0.0
      },
      {
        "time": "2025-10-02T02:00:00",
        "visibility": "unknown",
        "cloud_cover": {
          "total": 0.0
        },
        "fog_score": 0.0
      },
      {
        "time": "2025-10-02T03:00:00",
        "visibility": "unknown",
        "cloud_cover": {
          "total": 0.0
        },
        "fog_score": 0.0
      },
      {
        "time": "2025-10-02T04:00:00",
        "visibility": "unknown",
        "cloud_cover": {
          "total": 21
        },
        "fog_score": 2.1
      },
      {
        "time": "2025-10-02T05:00:00",
        "visibility": "unknown",
        "cloud_cover": {
          "total": 33
        },
        "fog_score": 3.3
      },
      {
        "time": "2025-10-02T06:00:00",
        "visibility": "unknown",
        "cloud_cover": {
          "total": 32
        },
        "fog_score": 3.2
      },
      {
        "time": "2025-10-02T07:00:00",
        "visibility": "unknown",
        "cloud_cover": {
          "total": 31
        },
        "fog_score": 3.1
      },
      {
        "time": "2025-10-02T08:00:00",
        "visibility": "unknown",
        "cloud_cover": {
          "total": 41
        },
        "fog_score": 4.1
      }
    ],
    "twilight_phases": [
      {
        "label": "Civil Twilight",
        "start": "6:23 AM",
        "end": "6:48 AM",
        "avg_fog_score": null
      },
      {
        "label": "Golden Hour",
        "start": "6:48 AM",
        "end": "7:48 AM",
        "avg_fog_score": null
      }
    ],
    "recommended_shoot_time": null,
    "summary_text": "No optimal low-fog window during twilight today. Consider shooting at sunset or when fog clears.",
    "updated_at": "2025-10-02T04:06:03.226622+00:00"
  },
  "san-diego": {
    "sunrise": "6:43 AM",
    "sunset": "6:31 PM",
    "solar_noon": "12:38 PM",
    "civil_twilight_begin": "6:18 AM",
    "civil_twilight_end": "6:56 PM",
    "nautical_twilight_begin": "6:18 AM",
    "nautical_twilight_end": "6:56 PM",
    "astronomical_twilight_begin": "6:18 AM",
    "astronomical_twilight_end": "6:56 PM",
    "day_length": 42435,
    "sunrise_score": 7,
    "sunset_score": 7,
    "moon_phase": {
      "value": 9.21,
      "label": "Waxing Gibbous",
      "moonrise": "4:06 PM",
      "moonset": "1:44 AM"
    },
    "fog_forecast": [
      {
        "time": "2025-10-01T21:00:00",
        "visibility": "unknown",
        "cloud_cover": {
          "total": 21
        },
        "fog_score": 2.1
      },
      {
        "time": "2025-10-01T22:00:00",
        "visibility": "unknown",
        "cloud_cover": {
          "total": 23
        },
        "fog_score": 2.3
      },
      {
        "time": "2025-10-01T23:00:00",
        "visibility": "unknown",
        "cloud_cover": {
          "total": 22
        },
        "fog_score": 2.2
      },
      {
        "time": "2025-10-02T00:00:00",
        "visibility": "unknown",
        "cloud_cover": {
          "total": 20
        },
        "fog_score": 2.0
      },
      {
        "time": "2025-10-02T01:00:00",
        "visibility": "unknown",
        "cloud_cover": {
          "total": 32
        },
        "fog_score": 3.2
      },
      {
        "time": "2025-10-02T02:00:00",
        "visibility": "unknown",
        "cloud_cover": {
          "total": 35
        },
        "fog_score": 3.5
      },
      {
        "time": "2025-10-02T03:00:00",
        "visibility": "unknown",
        "cloud_cover": {
          "total": 32
        },
        "fog_score": 3.2
      },
      {
        "time": "2025-10-02T04:00:00",
        "visibility": "unknown",
        "cloud_cover": {
          "total": 31
        },
        "fog_score": 3.1
      },
      {
        "time": "2025-10-02T05:00:00",
        "visibility": "unknown",
        "cloud_cover": {
          "total": 29
        },
        "fog_score": 2.9
      },
      {
        "time": "2025-10-02T06:00:00",
        "visibility": "unknown",
        "cloud_cover": {
          "total": 28
        },
        "fog_score": 2.8
      },
      {
        "time": "2025-10-02T07:00:00",
        "visibility": "unknown",
        "cloud_cover": {
          "total": 30
        },
        "fog_score": 3.0
      },
      {
        "time": "2025-10-02T08:00:00",
        "visibility": "unknown",
        "cloud_cover": {
          "total": 24
        },
        "fog_score": 2.4
      }
    ],
    "twilight_phases": [
      {
        "label": "Civil Twilight",
        "start": "6:18 AM",
        "end": "6:43 AM",
        "avg_fog_score": null
      },
      {
        "label": "Golden Hour",
        "start": "6:43 AM",
        "end": "7:43 AM",
        "avg_fog_score": null
      }
    ],
    "recommended_shoot_time": null,
    "summary_text": "No optimal low-fog window during twilight today. Consider shooting at sunset or when fog clears.",
    "updated_at": "2025-10-02T04:06:04.110929+00:00"
  },
  "lake-tahoe": {
    "sunrise": "6:57 AM",
    "sunset": "6:40 PM",
    "solar_noon": "12:49 PM",
    "civil_twilight_begin": "6:30 AM",
    "civil_twilight_end": "7:07 PM",
    "nautical_twilight_begin": "6:30 AM",
    "nautical_twilight_end": "7:07 PM",
    "astronomical_twilight_begin": "6:30 AM",
    "astronomical_twilight_end": "7:07 PM",
    "day_length": 42152,
    "sunrise_score": 2,
    "sunset_score": 3,
    "moon_phase": {
      "value": 9.21,
      "label": "Waxing Gibbous",
      "moonrise": "4:32 PM",
      "moonset": "1:38 AM"
    },
    "fog_forecast": [
      {
        "time": "2025-10-01T21:00:00",
        "visibility": "unknown",
        "cloud_cover": {
          "total": 65
        },
        "fog_score": 6.5
      },
      {
        "time": "2025-10-01T22:00:00",
        "visibility": "unknown",
        "cloud_cover": {
          "total": 48
        },
        "fog_score": 4.8
      },
      {
        "time": "2025-10-01T23:00:00",
        "visibility": "unknown",
        "cloud_cover": {
          "total": 44
        },
        "fog_score": 4.4
      },
      {
        "time": "2025-10-02T00:00:00",
        "visibility": "unknown",
        "cloud_cover": {
          "total": 51
        },
        "fog_score": 5.1
      },
      {
        "time": "2025-10-02T01:00:00",
        "visibility": "unknown",
        "cloud_cover": {
          "total": 73
        },
        "fog_score": 7.3
      },
      {
        "time": "2025-10-02T02:00:00",
        "visibility": "unknown",
        "cloud_cover": {
          "total": 97
        },
        "fog_score": 9.7
      },
      {
        "time": "2025-10-02T03:00:00",
        "visibility": "unknown",
        "cloud_cover": {
          "total": 90
        },
        "fog_score": 9.0
      },
      {
        "time": "2025-10-02T04:00:00",
        "visibility": "unknown",
        "cloud_cover": {
          "total": 73
        },
        "fog_score": 7.3
      },
      {
        "time": "2025-10-02T05:00:00",
        "visibility": "unknown",
        "cloud_cover": {
          "total": 80
        },
        "fog_score": 8.0
      },
      {
        "time": "2025-10-02T06:00:00",
        "visibility": "unknown",
        "cloud_cover": {
          "total": 100
        },
        "fog_score": 10.0
      },
      {
        "time": "2025-10-02T07:00:00",
        "visibility": "unknown",
        "cloud_cover": {
          "total": 97
        },
        "fog_score": 9.7
      },
      {
        "time": "2025-10-02T08:00:00",
        "visibility": "unknown",
        "cloud_cover": {
          "total": 96
        },
        "fog_score": 9.6
      }
    ],
    "twilight_phases": [
      {
        "label": "Civil Twilight",
        "start": "6:30 AM",
        "end": "6:57 AM",
        "avg_fog_score": null
      },
      {
        "label": "Golden Hour",
        "start": "6:57 AM",
        "end": "7:57 AM",
        "avg_fog_score": null
      }
    ],
    "recommended_shoot_time": null,
    "summary_text": "No optimal low-fog window during twilight today. Consider shooting at sunset or when fog clears.",
    "updated_at": "2025-10-02T04:06:05.093290+00:00"
  },
  "truckee": {
    "sunrise": "6:58 AM",
    "sunset": "6:40 PM",
    "solar_noon": "12:50 PM",
    "civil_twilight_begin": "6:31 AM",
    "civil_twilight_end": "7:07 PM",
    "nautical_twilight_begin": "6:31 AM",
    "nautical_twilight_end": "7:07 PM",
    "astronomical_twilight_begin": "6:31 AM",
    "astronomical_twilight_end": "7:07 PM",
    "day_length": 42141,
    "sunrise_score": 2,
    "sunset_score": 8,
    "moon_phase": {
      "value": 9.21,
      "label": "Waxing Gibbous",
      "moonrise": "4:33 PM",
      "moonset": "1:38 AM"
    },
    "fog_forecast": [
      {
        "time": "2025-10-01T21:00:00",
        "visibility": "unknown",
        "cloud_cover": {
          "total": 66
        },
        "fog_score": 6.6
      },
      {
        "time": "2025-10-01T22:00:00",
        "visibility": "unknown",
        "cloud_cover": {
          "total": 66
        },
        "fog_score": 6.6
      },
      {
        "time": "2025-10-01T23:00:00",
        "visibility": "unknown",
        "cloud_cover": {
          "total": 62
        },
        "fog_score": 6.2
      },
      {
        "time": "2025-10-02T00:00:00",
        "visibility": "unknown",
        "cloud_cover": {
          "total": 49
        },
        "fog_score": 4.9
      },
      {
        "time": "2025-10-02T01:00:00",
        "visibility": "unknown",
        "cloud_cover": {
          "total": 97
        },
        "fog_score": 9.7
      },
      {
        "time": "2025-10-02T02:00:00",
        "visibility": "unknown",
        "cloud_cover": {
          "total": 98
        },
        "fog_score": 9.8
      },
      {
        "time": "2025-10-02T03:00:00",
        "visibility": "unknown",
        "cloud_cover": {
          "total": 98
        },
        "fog_score": 9.8
      },
      {
        "time": "2025-10-02T04:00:00",
        "visibility": "unknown",
        "cloud_cover": {
          "total": 100
        },
        "fog_score": 10.0
      },
      {
        "time": "2025-10-02T05:00:00",
        "visibility": "unknown",
        "cloud_cover": {
          "total": 100
        },
        "fog_score": 10.0
      },
      {
        "time": "2025-10-02T06:00:00",
        "visibility": "unknown",
        "cloud_cover": {
          "total": 100
        },
        "fog_score": 10.0
      },
      {
        "time": "2025-10-02T07:00:00",
        "visibility": "unknown",
        "cloud_cover": {
          "total": 95
        },
        "fog_score": 9.5
      },
      {
        "time": "2025-10-02T08:00:00",
        "visibility": "unknown",
        "cloud_cover": {
          "total": 100
        },
        "fog_score": 10.0
      }
    ],
    "twilight_phases": [
      {
        "label": "Civil Twilight",
        "start": "6:31 AM",
        "end": "6:58 AM",
        "avg_fog_score": null
      },
      {
        "label": "Golden Hour",
        "start": "6:58 AM",
        "end": "7:58 AM",
        "avg_fog_score": null
      }
    ],
    "recommended_shoot_time": null,
    "summary_text": "No optimal low-fog window during twilight today. Consider shooting at sunset or when fog clears.",
    "updated_at": "2025-10-02T04:06:05.697301+00:00"
  },
  "tokyo": {
    "sunrise": "5:36 AM",
    "sunset": "5:23 PM",
    "solar_noon": "11:30 AM",
    "civil_twilight_begin": "5:11 AM",
    "civil_twilight_end": "5:49 PM",
    "nautical_twilight_begin": "5:11 AM",
    "nautical_twilight_end": "5:49 PM",
    "astronomical_twilight_begin": "5:11 AM",
    "astronomical_twilight_end": "5:49 PM",
    "day_length": 42404,
    "sunrise_score": 10,
    "sunset_score": 6,
    "moon_phase": {
      "value": 9.21,
      "label": "Waxing Gibbous",
      "moonrise": "2:41 PM",
      "moonset": "12:48 AM"
    },
    "fog_forecast": [
      {
        "time": "2025-10-02T13:00:00",
        "visibility": "unknown",
        "cloud_cover": {
          "total": 8
        },
        "fog_score": 0.8
      },
      {
        "time": "2025-10-02T14:00:00",
        "visibility": "unknown",
        "cloud_cover": {
          "total": 41
        },
        "fog_score": 4.1
      },
      {
        "time": "2025-10-02T15:00:00",
        "visibility": "unknown",
        "cloud_cover": {
          "total": 80
        },
        "fog_score": 8.0
      },
      {
        "time": "2025-10-02T16:00:00",
        "visibility": "unknown",
        "cloud_cover": {
          "total": 100
        },
        "fog_score": 10.0
      },
      {
        "time": "2025-10-02T17:00:00",
        "visibility": "unknown",
        "cloud_cover": {
          "total": 90
        },
        "fog_score": 9.0
      },
      {
        "time": "2025-10-02T18:00:00",
        "visibility": "unknown",
        "cloud_cover": {
          "total": 100
        },
        "fog_score": 10.0
      },
      {
        "time": "2025-10-02T19:00:00",
        "visibility": "unknown",
        "cloud_cover": {
          "total": 100
        },
        "fog_score": 10.0
      },
      {
        "time": "2025-10-02T20:00:00",
        "visibility": "unknown",
        "cloud_cover": {
          "total": 100
        },
        "fog_score": 10.0
      },
      {
        "time": "2025-10-02T21:00:00",
        "visibility": "unknown",
        "cloud_cover": {
          "total": 100
        },
        "fog_score": 10.0
      },
      {
        "time": "2025-10-02T22:00:00",
        "visibility": "unknown",
        "cloud_cover": {
          "total": 100
        },
        "fog_score": 10.0
      },
      {
        "time": "2025-10-02T23:00:00",
        "visibility": "unknown",
        "cloud_cover": {
          "total": 100
        },
        "fog_score": 10.0
      },
      {
        "time": "2025-10-03T00:00:00",
        "visibility": "unknown",
        "cloud_cover": {
          "total": 100
        },
        "fog_score": 10.0
      }
    ],
    "twilight_phases": [
      {
        "label": "Civil Twilight",
        "start": "5:11 AM",
        "end": "5:36 AM",
        "avg_fog_score": null
      },
      {
        "label": "Golden Hour",
        "start": "5:36 AM",
        "end": "6:36 AM",
        "avg_fog_score": null
      }
    ],
    "recommended_shoot_time": null,
    "summary_text": "No optimal low-fog window during twilight today. Consider shooting at sunset or when fog clears.",
    "updated_at": "2025-10-02T04:06:06.293294+00:00"
  }
}